{  
    "H4FPn4X1RfR9RQtmFzY6BRozUAfoR3Ejp": {
        "minerData":[  
        {  
            "timestamp":"2018-08-11T12:29:38.000Z",
            "workers":1,
            "valid_hashes":48684,
            "stale_hashes":0,
            "pending_hashes":0
        },
        {  
            "timestamp":"2018-08-11T12:31:19.000Z",
            "workers":2,
            "valid_hashes":2551504,
            "stale_hashes":0,
            "pending_hashes":0
        },
        {  
            "timestamp":"2018-08-11T12:40:06.000Z",
            "workers":2,
            "valid_hashes":1786216,
            "stale_hashes":0,
            "pending_hashes":0
        },
        {  
            "timestamp":"2018-08-11T12:52:12.000Z",
            "workers":2,
            "valid_hashes":1708487,
            "stale_hashes":0,
            "pending_hashes":0
        },
        {  
            "timestamp":"2018-08-11T13:00:03.000Z",
            "workers":2,
            "valid_hashes":1894574,
            "stale_hashes":0,
            "pending_hashes":0
        },
        {  
            "timestamp":"2018-08-11T13:10:05.000Z",
            "workers":2,
            "valid_hashes":2416697,
            "stale_hashes":0,
            "pending_hashes":0
        },
        {  
            "timestamp":"2018-08-11T13:20:10.000Z",
            "workers":2,
            "valid_hashes":2023818,
            "stale_hashes":0,
            "pending_hashes":0
        },
        {  
            "timestamp":"2018-08-11T13:30:08.000Z",
            "workers":2,
            "valid_hashes":1657531,
            "stale_hashes":0,
            "pending_hashes":0
        },
        {  
            "timestamp":"2018-08-11T13:41:50.000Z",
            "workers":2,
            "valid_hashes":1360719,
            "stale_hashes":0,
            "pending_hashes":0
        },
        {  
            "timestamp":"2018-08-11T13:50:36.000Z",
            "workers":2,
            "valid_hashes":1926547,
            "stale_hashes":0,
            "pending_hashes":0
        },
        {  
            "timestamp":"2018-08-11T14:00:43.000Z",
            "workers":2,
            "valid_hashes":1544836,
            "stale_hashes":0,
            "pending_hashes":0
        },
        {  
            "timestamp":"2018-08-11T14:10:23.000Z",
            "workers":2,
            "valid_hashes":2294933,
            "stale_hashes":0,
            "pending_hashes":0
        },
        {  
            "timestamp":"2018-08-11T14:20:04.000Z",
            "workers":2,
            "valid_hashes":2446690,
            "stale_hashes":0,
            "pending_hashes":0
        },
        {  
            "timestamp":"2018-08-11T14:33:09.000Z",
            "workers":2,
            "valid_hashes":1569074,
            "stale_hashes":0,
            "pending_hashes":0
        },
        {  
            "timestamp":"2018-08-11T14:40:21.000Z",
            "workers":2,
            "valid_hashes":803217,
            "stale_hashes":0,
            "pending_hashes":0
        },
        {  
            "timestamp":"2018-08-11T14:50:40.000Z",
            "workers":2,
            "valid_hashes":2696875,
            "stale_hashes":0,
            "pending_hashes":0
        },
        {  
            "timestamp":"2018-08-11T15:02:09.000Z",
            "workers":2,
            "valid_hashes":2666807,
            "stale_hashes":0,
            "pending_hashes":0
        },
        {  
            "timestamp":"2018-08-11T15:10:41.000Z",
            "workers":2,
            "valid_hashes":1147292,
            "stale_hashes":0,
            "pending_hashes":0
        },
        {  
            "timestamp":"2018-08-11T15:20:47.000Z",
            "workers":2,
            "valid_hashes":1779435,
            "stale_hashes":0,
            "pending_hashes":0
        },
        {  
            "timestamp":"2018-08-11T15:30:05.000Z",
            "workers":2,
            "valid_hashes":1654851,
            "stale_hashes":0,
            "pending_hashes":0
        },
        {  
            "timestamp":"2018-08-11T15:40:21.000Z",
            "workers":2,
            "valid_hashes":2209371,
            "stale_hashes":0,
            "pending_hashes":0
        },
        {  
            "timestamp":"2018-08-11T15:50:27.000Z",
            "workers":2,
            "valid_hashes":3004276,
            "stale_hashes":0,
            "pending_hashes":0
        },
        {  
            "timestamp":"2018-08-11T16:00:30.000Z",
            "workers":2,
            "valid_hashes":2355703,
            "stale_hashes":0,
            "pending_hashes":0
        },
        {  
            "timestamp":"2018-08-11T16:11:24.000Z",
            "workers":2,
            "valid_hashes":2542142,
            "stale_hashes":0,
            "pending_hashes":0
        },
        {  
            "timestamp":"2018-08-11T16:20:09.000Z",
            "workers":2,
            "valid_hashes":2250951,
            "stale_hashes":0,
            "pending_hashes":0
        },
        {  
            "timestamp":"2018-08-11T16:30:11.000Z",
            "workers":2,
            "valid_hashes":3079959,
            "stale_hashes":0,
            "pending_hashes":0
        },
        {  
            "timestamp":"2018-08-11T16:40:05.000Z",
            "workers":2,
            "valid_hashes":1417105,
            "stale_hashes":0,
            "pending_hashes":0
        },
        {  
            "timestamp":"2018-08-11T16:50:34.000Z",
            "workers":2,
            "valid_hashes":2106920,
            "stale_hashes":0,
            "pending_hashes":0
        },
        {  
            "timestamp":"2018-08-11T17:00:24.000Z",
            "workers":2,
            "valid_hashes":3093586,
            "stale_hashes":0,
            "pending_hashes":0
        },
        {  
            "timestamp":"2018-08-11T17:12:33.000Z",
            "workers":2,
            "valid_hashes":2859695,
            "stale_hashes":0,
            "pending_hashes":0
        },
        {  
            "timestamp":"2018-08-11T17:21:52.000Z",
            "workers":2,
            "valid_hashes":1905355,
            "stale_hashes":0,
            "pending_hashes":0
        },
        {  
            "timestamp":"2018-08-11T17:30:17.000Z",
            "workers":2,
            "valid_hashes":1537518,
            "stale_hashes":0,
            "pending_hashes":0
        },
        {  
            "timestamp":"2018-08-11T17:40:34.000Z",
            "workers":2,
            "valid_hashes":1698011,
            "stale_hashes":0,
            "pending_hashes":0
        },
        {  
            "timestamp":"2018-08-11T17:50:02.000Z",
            "workers":2,
            "valid_hashes":2225728,
            "stale_hashes":0,
            "pending_hashes":0
        },
        {  
            "timestamp":"2018-08-11T18:00:19.000Z",
            "workers":2,
            "valid_hashes":2079688,
            "stale_hashes":0,
            "pending_hashes":0
        },
        {  
            "timestamp":"2018-08-11T18:11:17.000Z",
            "workers":2,
            "valid_hashes":981700,
            "stale_hashes":0,
            "pending_hashes":0
        },
        {  
            "timestamp":"2018-08-11T18:20:52.000Z",
            "workers":2,
            "valid_hashes":1137715,
            "stale_hashes":0,
            "pending_hashes":0
        },
        {  
            "timestamp":"2018-08-11T18:30:11.000Z",
            "workers":2,
            "valid_hashes":2693743,
            "stale_hashes":0,
            "pending_hashes":0
        },
        {  
            "timestamp":"2018-08-11T18:41:08.000Z",
            "workers":2,
            "valid_hashes":3555803,
            "stale_hashes":0,
            "pending_hashes":0
        },
        {  
            "timestamp":"2018-08-11T18:53:28.000Z",
            "workers":2,
            "valid_hashes":665898,
            "stale_hashes":0,
            "pending_hashes":0
        },
        {  
            "timestamp":"2018-08-11T19:01:17.000Z",
            "workers":2,
            "valid_hashes":2282248,
            "stale_hashes":0,
            "pending_hashes":0
        },
        {  
            "timestamp":"2018-08-11T19:10:09.000Z",
            "workers":2,
            "valid_hashes":1063611,
            "stale_hashes":0,
            "pending_hashes":0
        },
        {  
            "timestamp":"2018-08-11T19:20:35.000Z",
            "workers":2,
            "valid_hashes":1197692,
            "stale_hashes":0,
            "pending_hashes":0
        },
        {  
            "timestamp":"2018-08-11T19:30:06.000Z",
            "workers":2,
            "valid_hashes":2913419,
            "stale_hashes":0,
            "pending_hashes":0
        },
        {  
            "timestamp":"2018-08-11T19:40:17.000Z",
            "workers":2,
            "valid_hashes":1311961,
            "stale_hashes":0,
            "pending_hashes":0
        },
        {  
            "timestamp":"2018-08-11T19:50:43.000Z",
            "workers":2,
            "valid_hashes":2020337,
            "stale_hashes":0,
            "pending_hashes":0
        },
        {  
            "timestamp":"2018-08-11T20:00:17.000Z",
            "workers":2,
            "valid_hashes":2272763,
            "stale_hashes":0,
            "pending_hashes":0
        },
        {  
            "timestamp":"2018-08-11T20:10:58.000Z",
            "workers":2,
            "valid_hashes":1931293,
            "stale_hashes":0,
            "pending_hashes":0
        },
        {  
            "timestamp":"2018-08-11T20:21:51.000Z",
            "workers":2,
            "valid_hashes":1003971,
            "stale_hashes":0,
            "pending_hashes":0
        },
        {  
            "timestamp":"2018-08-11T20:30:04.000Z",
            "workers":2,
            "valid_hashes":1698515,
            "stale_hashes":0,
            "pending_hashes":0
        },
        {  
            "timestamp":"2018-08-11T20:40:23.000Z",
            "workers":2,
            "valid_hashes":2174877,
            "stale_hashes":0,
            "pending_hashes":0
        },
        {  
            "timestamp":"2018-08-11T20:50:15.000Z",
            "workers":2,
            "valid_hashes":929483,
            "stale_hashes":0,
            "pending_hashes":0
        },
        {  
            "timestamp":"2018-08-11T21:00:19.000Z",
            "workers":2,
            "valid_hashes":2514565,
            "stale_hashes":0,
            "pending_hashes":0
        },
        {  
            "timestamp":"2018-08-11T21:11:16.000Z",
            "workers":2,
            "valid_hashes":2995133,
            "stale_hashes":0,
            "pending_hashes":0
        },
        {  
            "timestamp":"2018-08-11T21:20:01.000Z",
            "workers":2,
            "valid_hashes":2048409,
            "stale_hashes":0,
            "pending_hashes":0
        },
        {  
            "timestamp":"2018-08-11T21:30:00.000Z",
            "workers":2,
            "valid_hashes":1783948,
            "stale_hashes":0,
            "pending_hashes":0
        },
        {  
            "timestamp":"2018-08-11T21:41:32.000Z",
            "workers":2,
            "valid_hashes":1874306,
            "stale_hashes":0,
            "pending_hashes":0
        },
        {  
            "timestamp":"2018-08-11T21:51:02.000Z",
            "workers":2,
            "valid_hashes":1398094,
            "stale_hashes":0,
            "pending_hashes":0
        },
        {  
            "timestamp":"2018-08-11T22:02:06.000Z",
            "workers":2,
            "valid_hashes":1109575,
            "stale_hashes":0,
            "pending_hashes":0
        },
        {  
            "timestamp":"2018-08-11T22:10:24.000Z",
            "workers":2,
            "valid_hashes":1591557,
            "stale_hashes":0,
            "pending_hashes":0
        },
        {  
            "timestamp":"2018-08-11T22:20:46.000Z",
            "workers":2,
            "valid_hashes":1663225,
            "stale_hashes":0,
            "pending_hashes":0
        },
        {  
            "timestamp":"2018-08-11T22:30:10.000Z",
            "workers":2,
            "valid_hashes":1307873,
            "stale_hashes":0,
            "pending_hashes":0
        },
        {  
            "timestamp":"2018-08-11T22:40:00.000Z",
            "workers":2,
            "valid_hashes":1496270,
            "stale_hashes":0,
            "pending_hashes":0
        },
        {  
            "timestamp":"2018-08-11T22:50:09.000Z",
            "workers":2,
            "valid_hashes":1889462,
            "stale_hashes":0,
            "pending_hashes":0
        },
        {  
            "timestamp":"2018-08-11T23:00:06.000Z",
            "workers":2,
            "valid_hashes":1773659,
            "stale_hashes":0,
            "pending_hashes":0
        },
        {  
            "timestamp":"2018-08-11T23:10:25.000Z",
            "workers":2,
            "valid_hashes":1637125,
            "stale_hashes":0,
            "pending_hashes":0
        },
        {  
            "timestamp":"2018-08-11T23:20:38.000Z",
            "workers":2,
            "valid_hashes":3187511,
            "stale_hashes":0,
            "pending_hashes":0
        },
        {  
            "timestamp":"2018-08-11T23:30:35.000Z",
            "workers":2,
            "valid_hashes":1564222,
            "stale_hashes":0,
            "pending_hashes":0
        },
        {  
            "timestamp":"2018-08-11T23:40:19.000Z",
            "workers":2,
            "valid_hashes":1877030,
            "stale_hashes":0,
            "pending_hashes":0
        },
        {  
            "timestamp":"2018-08-11T23:51:40.000Z",
            "workers":2,
            "valid_hashes":1587610,
            "stale_hashes":0,
            "pending_hashes":0
        },
        {  
            "timestamp":"2018-08-12T00:02:59.000Z",
            "workers":2,
            "valid_hashes":892705,
            "stale_hashes":0,
            "pending_hashes":0
        },
        {  
            "timestamp":"2018-08-12T00:10:19.000Z",
            "workers":2,
            "valid_hashes":1751072,
            "stale_hashes":0,
            "pending_hashes":0
        },
        {  
            "timestamp":"2018-08-12T00:20:25.000Z",
            "workers":2,
            "valid_hashes":2119615,
            "stale_hashes":0,
            "pending_hashes":0
        },
        {  
            "timestamp":"2018-08-12T00:31:13.000Z",
            "workers":2,
            "valid_hashes":1510998,
            "stale_hashes":0,
            "pending_hashes":0
        },
        {  
            "timestamp":"2018-08-12T00:40:52.000Z",
            "workers":2,
            "valid_hashes":1258036,
            "stale_hashes":0,
            "pending_hashes":0
        },
        {  
            "timestamp":"2018-08-12T00:50:04.000Z",
            "workers":2,
            "valid_hashes":2314096,
            "stale_hashes":0,
            "pending_hashes":0
        },
        {  
            "timestamp":"2018-08-12T01:00:36.000Z",
            "workers":2,
            "valid_hashes":2280085,
            "stale_hashes":0,
            "pending_hashes":0
        },
        {  
            "timestamp":"2018-08-12T01:11:45.000Z",
            "workers":2,
            "valid_hashes":1128645,
            "stale_hashes":0,
            "pending_hashes":0
        },
        {  
            "timestamp":"2018-08-12T01:20:34.000Z",
            "workers":2,
            "valid_hashes":1970681,
            "stale_hashes":0,
            "pending_hashes":0
        },
        {  
            "timestamp":"2018-08-12T01:30:17.000Z",
            "workers":2,
            "valid_hashes":1850069,
            "stale_hashes":0,
            "pending_hashes":0
        },
        {  
            "timestamp":"2018-08-12T01:40:14.000Z",
            "workers":2,
            "valid_hashes":1334582,
            "stale_hashes":0,
            "pending_hashes":0
        },
        {  
            "timestamp":"2018-08-12T01:50:02.000Z",
            "workers":2,
            "valid_hashes":2346073,
            "stale_hashes":0,
            "pending_hashes":0
        },
        {  
            "timestamp":"2018-08-12T02:01:44.000Z",
            "workers":2,
            "valid_hashes":3054197,
            "stale_hashes":0,
            "pending_hashes":0
        },
        {  
            "timestamp":"2018-08-12T02:11:48.000Z",
            "workers":1,
            "valid_hashes":960243,
            "stale_hashes":0,
            "pending_hashes":0
        },
        {  
            "timestamp":"2018-08-12T02:20:18.000Z",
            "workers":2,
            "valid_hashes":1879971,
            "stale_hashes":0,
            "pending_hashes":0
        },
        {  
            "timestamp":"2018-08-12T02:30:08.000Z",
            "workers":2,
            "valid_hashes":1718673,
            "stale_hashes":0,
            "pending_hashes":0
        },
        {  
            "timestamp":"2018-08-12T02:41:22.000Z",
            "workers":2,
            "valid_hashes":1904542,
            "stale_hashes":0,
            "pending_hashes":0
        },
        {  
            "timestamp":"2018-08-12T02:50:46.000Z",
            "workers":2,
            "valid_hashes":1107670,
            "stale_hashes":0,
            "pending_hashes":0
        },
        {  
            "timestamp":"2018-08-12T03:02:21.000Z",
            "workers":2,
            "valid_hashes":2156440,
            "stale_hashes":0,
            "pending_hashes":0
        },
        {  
            "timestamp":"2018-08-12T03:10:07.000Z",
            "workers":2,
            "valid_hashes":1145907,
            "stale_hashes":0,
            "pending_hashes":0
        },
        {  
            "timestamp":"2018-08-12T03:20:31.000Z",
            "workers":2,
            "valid_hashes":1679165,
            "stale_hashes":0,
            "pending_hashes":0
        },
        {  
            "timestamp":"2018-08-12T03:30:07.000Z",
            "workers":2,
            "valid_hashes":2415565,
            "stale_hashes":0,
            "pending_hashes":0
        },
        {  
            "timestamp":"2018-08-12T03:40:40.000Z",
            "workers":2,
            "valid_hashes":1199147,
            "stale_hashes":0,
            "pending_hashes":0
        },
        {  
            "timestamp":"2018-08-12T03:50:02.000Z",
            "workers":2,
            "valid_hashes":1532357,
            "stale_hashes":0,
            "pending_hashes":0
        },
        {  
            "timestamp":"2018-08-12T04:00:13.000Z",
            "workers":2,
            "valid_hashes":2045261,
            "stale_hashes":0,
            "pending_hashes":0
        },
        {  
            "timestamp":"2018-08-12T04:10:41.000Z",
            "workers":2,
            "valid_hashes":1729725,
            "stale_hashes":0,
            "pending_hashes":0
        },
        {  
            "timestamp":"2018-08-12T04:22:04.000Z",
            "workers":2,
            "valid_hashes":866698,
            "stale_hashes":0,
            "pending_hashes":0
        },
        {  
            "timestamp":"2018-08-12T04:30:11.000Z",
            "workers":2,
            "valid_hashes":1971850,
            "stale_hashes":0,
            "pending_hashes":0
        },
        {  
            "timestamp":"2018-08-12T04:40:30.000Z",
            "workers":2,
            "valid_hashes":2015943,
            "stale_hashes":0,
            "pending_hashes":0
        },
        {  
            "timestamp":"2018-08-12T04:51:39.000Z",
            "workers":2,
            "valid_hashes":2403713,
            "stale_hashes":0,
            "pending_hashes":0
        },
        {  
            "timestamp":"2018-08-12T05:01:47.000Z",
            "workers":2,
            "valid_hashes":1765489,
            "stale_hashes":0,
            "pending_hashes":0
        },
        {  
            "timestamp":"2018-08-12T05:10:14.000Z",
            "workers":2,
            "valid_hashes":1781022,
            "stale_hashes":0,
            "pending_hashes":0
        },
        {  
            "timestamp":"2018-08-12T05:20:46.000Z",
            "workers":2,
            "valid_hashes":1730633,
            "stale_hashes":0,
            "pending_hashes":0
        },
        {  
            "timestamp":"2018-08-12T05:30:05.000Z",
            "workers":2,
            "valid_hashes":1752111,
            "stale_hashes":0,
            "pending_hashes":0
        },
        {  
            "timestamp":"2018-08-12T05:41:35.000Z",
            "workers":2,
            "valid_hashes":1759923,
            "stale_hashes":0,
            "pending_hashes":0
        },
        {  
            "timestamp":"2018-08-12T05:50:15.000Z",
            "workers":2,
            "valid_hashes":1539160,
            "stale_hashes":0,
            "pending_hashes":0
        },
        {  
            "timestamp":"2018-08-12T06:00:38.000Z",
            "workers":2,
            "valid_hashes":1657303,
            "stale_hashes":0,
            "pending_hashes":0
        },
        {  
            "timestamp":"2018-08-12T06:10:00.000Z",
            "workers":2,
            "valid_hashes":3233475,
            "stale_hashes":0,
            "pending_hashes":0
        },
        {  
            "timestamp":"2018-08-12T06:21:00.000Z",
            "workers":2,
            "valid_hashes":1505601,
            "stale_hashes":0,
            "pending_hashes":0
        },
        {  
            "timestamp":"2018-08-12T06:30:23.000Z",
            "workers":2,
            "valid_hashes":1255948,
            "stale_hashes":0,
            "pending_hashes":0
        },
        {  
            "timestamp":"2018-08-12T06:40:11.000Z",
            "workers":2,
            "valid_hashes":2376682,
            "stale_hashes":0,
            "pending_hashes":0
        },
        {  
            "timestamp":"2018-08-12T06:50:11.000Z",
            "workers":2,
            "valid_hashes":3892912,
            "stale_hashes":0,
            "pending_hashes":0
        },
        {  
            "timestamp":"2018-08-12T07:00:21.000Z",
            "workers":2,
            "valid_hashes":1562703,
            "stale_hashes":0,
            "pending_hashes":0
        }
        ],
        "minerPayouts":[  
        {  
            "address":"H4FPn4X1RfR9RQtmFzY6BRozUAfoR3Ejp",
            "txid":"8Jo56cvGigFbtHG9EhuBa43t2jPwxKuhsmxM7q4aZAvj",
            "timestamp":"2018-08-12T03:19:33.000Z",
            "paidFee":0.0025,
            "paidAmount":4236876802
        },
        {  
            "address":"H4FPn4X1RfR9RQtmFzY6BRozUAfoR3Ejp",
            "txid":"8ohnE9piZPj83J4MgaTY4JmWaaKLhctSD4hhtFVhVfrb",
            "timestamp":"2018-08-12T03:02:21.000Z",
            "paidFee":0.0025,
            "paidAmount":4474192716
        },
        {  
            "address":"H4FPn4X1RfR9RQtmFzY6BRozUAfoR3Ejp",
            "txid":"47FtkLFvCgzCQo5XQeiFugLjTouA5QXhwr2drDenQYJa",
            "timestamp":"2018-08-11T23:49:00.000Z",
            "paidFee":0.0025,
            "paidAmount":4094824724
        },
        {  
            "address":"H4FPn4X1RfR9RQtmFzY6BRozUAfoR3Ejp",
            "txid":"6MUitTjcjj1Srig24hwuenWrxq1jzfg4FNdE39j7Vi3D",
            "timestamp":"2018-08-11T22:43:49.000Z",
            "paidFee":0.0025,
            "paidAmount":307936
        },
        {  
            "address":"H4FPn4X1RfR9RQtmFzY6BRozUAfoR3Ejp",
            "txid":"9UQXUP8p2VfGo5tFHkjFpAEVMP6Yas1saBGFYRd9VstC",
            "timestamp":"2018-08-11T22:03:54.000Z",
            "paidFee":0.0025,
            "paidAmount":3267717762
        },
        {  
            "address":"H4FPn4X1RfR9RQtmFzY6BRozUAfoR3Ejp",
            "txid":"7GdqYKTY4HpWkJKh191prrAmaZm7RhgfMnDKV3EETRaK",
            "timestamp":"2018-08-11T21:49:00.000Z",
            "paidFee":0.0025,
            "paidAmount":2951531622
        },
        {  
            "address":"H4FPn4X1RfR9RQtmFzY6BRozUAfoR3Ejp",
            "txid":"F1mRfH8rTjK8VTdohXWKktLC8YB6qYUh2Z4f8BupZ8Jz",
            "timestamp":"2018-08-11T21:11:16.000Z",
            "paidFee":0.0025,
            "paidAmount":5292794033
        },
        {  
            "address":"H4FPn4X1RfR9RQtmFzY6BRozUAfoR3Ejp",
            "txid":"68RSKJxPNwGNXSZ2kBCXRMr2yYpn91Qfo6QtCUdcThfe",
            "timestamp":"2018-08-11T19:30:06.000Z",
            "paidFee":0.0025,
            "paidAmount":5019537247
        },
        {  
            "address":"H4FPn4X1RfR9RQtmFzY6BRozUAfoR3Ejp",
            "txid":"4uPuxk1kB66q3QjRCCvYLWAmmYAZd2dXTMguUhfGgjHr",
            "timestamp":"2018-08-11T16:02:38.000Z",
            "paidFee":0.0025,
            "paidAmount":5132287658
        },
        {  
            "address":"H4FPn4X1RfR9RQtmFzY6BRozUAfoR3Ejp",
            "txid":"E8qodsDV7UsFWxBihBvN8FbjNR5wiCHDhyueRFta6tTd",
            "timestamp":"2018-08-11T16:00:30.000Z",
            "paidFee":0.0025,
            "paidAmount":2103121522
        },
        {  
            "address":"H4FPn4X1RfR9RQtmFzY6BRozUAfoR3Ejp",
            "txid":"9ycwdm6Dz6XAfYBGEDSjZtPFvY1ynnSUn3PFpWZ221dF",
            "timestamp":"2018-08-11T15:26:44.000Z",
            "paidFee":0.0025,
            "paidAmount":5490013690
        },
        {  
            "address":"H4FPn4X1RfR9RQtmFzY6BRozUAfoR3Ejp",
            "txid":"BJNaAPiSkvmGgELF6ZU23mru6fvFWqeftYZZbabdqDmt",
            "timestamp":"2018-08-11T14:50:40.000Z",
            "paidFee":0.0025,
            "paidAmount":5203944561
        },
        {  
            "address":"H4FPn4X1RfR9RQtmFzY6BRozUAfoR3Ejp",
            "txid":"9D31s7v5xVxQXSwHvrxDfTLUmDkxH7DFnagmspiZvaP4",
            "timestamp":"2018-08-11T14:33:09.000Z",
            "paidFee":0.0025,
            "paidAmount":3829877715
        },
        {  
            "address":"H4FPn4X1RfR9RQtmFzY6BRozUAfoR3Ejp",
            "txid":"88iDdEPcLWX82Yg5Fx4zc8KG9kLuk2bMaQoU8Dm4vvy6",
            "timestamp":"2018-08-11T12:07:54.000Z",
            "paidFee":0.0025,
            "paidAmount":4525965813
        },
        {  
            "address":"H4FPn4X1RfR9RQtmFzY6BRozUAfoR3Ejp",
            "txid":"Fkm42dkk5Zpvimf4EJpz3C7xLfR4tU2vX3dwoR3EMk4r",
            "timestamp":"2018-08-11T09:57:05.000Z",
            "paidFee":0.0025,
            "paidAmount":5341122728
        },
        {  
            "address":"H4FPn4X1RfR9RQtmFzY6BRozUAfoR3Ejp",
            "txid":"4bMqinGRt1dDBtcaWmbQXRRsh7kRWSuGP1YmnzSt5EBd",
            "timestamp":"2018-08-11T08:47:29.000Z",
            "paidFee":0.0025,
            "paidAmount":5522157868
        },
        {  
            "address":"H4FPn4X1RfR9RQtmFzY6BRozUAfoR3Ejp",
            "txid":"9HMNgY28Lu6tfpmz2TiQc2cKpnjvXd97kja7jPzavXy6",
            "timestamp":"2018-08-11T02:56:24.000Z",
            "paidFee":0.0025,
            "paidAmount":4808482377
        },
        {  
            "address":"H4FPn4X1RfR9RQtmFzY6BRozUAfoR3Ejp",
            "txid":"9ELjFXMjhpDqm52AWch8QdPnFMr4W6LZxYBBfwL67jaU",
            "timestamp":"2018-08-10T19:18:21.000Z",
            "paidFee":0.0025,
            "paidAmount":228726
        },
        {  
            "address":"H4FPn4X1RfR9RQtmFzY6BRozUAfoR3Ejp",
            "txid":"53CxMvt7KnqGigMwTRyAd2vXTJNqNpD16v5Kb3jRcj5R",
            "timestamp":"2018-08-10T19:07:58.000Z",
            "paidFee":0.0025,
            "paidAmount":7598497089
        },
        {  
            "address":"H4FPn4X1RfR9RQtmFzY6BRozUAfoR3Ejp",
            "txid":"4XJdfrZQrA6eju2vaMAP4sFWHR4kJjqpSHvT8ZU4iXwW",
            "timestamp":"2018-08-10T18:29:57.000Z",
            "paidFee":0.0025,
            "paidAmount":408599795
        },
        {  
            "address":"H4FPn4X1RfR9RQtmFzY6BRozUAfoR3Ejp",
            "txid":"5R7Mrs22MqZDM53BCbxQu2oS9QueHbvoD1j1WDydBBoH",
            "timestamp":"2018-08-10T17:28:27.000Z",
            "paidFee":0.0025,
            "paidAmount":3939122954
        },
        {  
            "address":"H4FPn4X1RfR9RQtmFzY6BRozUAfoR3Ejp",
            "txid":"7tdd5iBeumi2Uw9XEbNKe3o7nafMv8bMu69X2gVe5ery",
            "timestamp":"2018-08-10T15:02:22.000Z",
            "paidFee":0.0025,
            "paidAmount":1134355634
        },
        {  
            "address":"H4FPn4X1RfR9RQtmFzY6BRozUAfoR3Ejp",
            "txid":"BifxPomNJCu4ARw3vBqmwEM4j6655boVio5NMC9DMz26",
            "timestamp":"2018-08-10T14:36:21.000Z",
            "paidFee":0.00252,
            "paidAmount":2610423622
        },
        {  
            "address":"H4FPn4X1RfR9RQtmFzY6BRozUAfoR3Ejp",
            "txid":"GBFGffXXGzMWQo5nt8gVSYexxQNWPQShULYD9sMGN1Je",
            "timestamp":"2018-08-10T13:55:37.000Z",
            "paidFee":0.00255,
            "paidAmount":1210497638
        },
        {  
            "address":"H4FPn4X1RfR9RQtmFzY6BRozUAfoR3Ejp",
            "txid":"Bi9Yu7A4VwPimAFeKcrmn6dMhMPFdJcyTGcMoSCR5X5c",
            "timestamp":"2018-08-10T13:21:13.000Z",
            "paidFee":0.00261,
            "paidAmount":2554214415
        },
        {  
            "address":"H4FPn4X1RfR9RQtmFzY6BRozUAfoR3Ejp",
            "txid":"FCHL1wqQqytgYYjqJuFv95MRxTvWn2QsukU9a3Hw2qCP",
            "timestamp":"2018-08-10T12:40:40.000Z",
            "paidFee":0.00265,
            "paidAmount":2760993174
        },
        {  
            "address":"H4FPn4X1RfR9RQtmFzY6BRozUAfoR3Ejp",
            "txid":"8C6D32EQs78wvxoM1Kdyv5ZCP7NLgDK2kcubdcURGSvh",
            "timestamp":"2018-08-10T12:33:34.000Z",
            "paidFee":0.0027,
            "paidAmount":2661161919
        },
        {  
            "address":"H4FPn4X1RfR9RQtmFzY6BRozUAfoR3Ejp",
            "txid":"FvcNWnS4Mw59uXGACQPM3kfMpw7obQSJUMJfs36C9f12",
            "timestamp":"2018-08-10T12:07:01.000Z",
            "paidFee":0.00271,
            "paidAmount":2137128807
        },
        {  
            "address":"H4FPn4X1RfR9RQtmFzY6BRozUAfoR3Ejp",
            "txid":"Cx4J5V1387kEqPJ1hT3Q33efJhXXJFu7d5KunY54U76H",
            "timestamp":"2018-08-10T04:53:25.000Z",
            "paidFee":0.00274,
            "paidAmount":2305950
        },
        {  
            "address":"H4FPn4X1RfR9RQtmFzY6BRozUAfoR3Ejp",
            "txid":"AwKmnQ97Cmggr1hcWcZobfLP8iVzjcLic2XdTZaTaHga",
            "timestamp":"2018-08-10T04:50:36.000Z",
            "paidFee":0.00327,
            "paidAmount":1031633002
        },
        {  
            "address":"H4FPn4X1RfR9RQtmFzY6BRozUAfoR3Ejp",
            "txid":"7rEMSbuRhhD7mhhbnE5S9cpFt7jy72aJRWMUbVKtstJV",
            "timestamp":"2018-08-09T21:54:43.000Z",
            "paidFee":0.00327,
            "paidAmount":1821932091
        },
        {  
            "address":"H4FPn4X1RfR9RQtmFzY6BRozUAfoR3Ejp",
            "txid":"4pdEGDoay6aF59psvVkftJNxt56p6NFb7oPbcNeMtWGJ",
            "timestamp":"2018-08-09T14:55:42.000Z",
            "paidFee":0.00381,
            "paidAmount":1363491056
        },
        {  
            "address":"H4FPn4X1RfR9RQtmFzY6BRozUAfoR3Ejp",
            "txid":"K7zgrFbRXUtTrQU1b8evJrDpkyNwBgH3J3AGrJMMMEq",
            "timestamp":"2018-08-09T05:36:14.000Z",
            "paidFee":0.00429,
            "paidAmount":3681868708
        },
        {  
            "address":"H4FPn4X1RfR9RQtmFzY6BRozUAfoR3Ejp",
            "txid":"FqGQMYvpRSbVMfwmridbR6rCJs9XdPfY5A8pAJqKhyWJ",
            "timestamp":"2018-08-09T01:15:28.000Z",
            "paidFee":0.005,
            "paidAmount":3519787509
        },
        {  
            "address":"H4FPn4X1RfR9RQtmFzY6BRozUAfoR3Ejp",
            "txid":"6qc54rYSHwHTJcN675vzNWAFSmqxQCr4JVLiEemkpgCH",
            "timestamp":"2018-08-08T21:06:42.000Z",
            "paidFee":0.00535,
            "paidAmount":3438676343
        },
        {  
            "address":"H4FPn4X1RfR9RQtmFzY6BRozUAfoR3Ejp",
            "txid":"HR9FWqX2hYLsiWYWboj3pVkA96121esZ9DbfPnsVALTu",
            "timestamp":"2018-08-08T20:20:23.000Z",
            "paidFee":0.00565,
            "paidAmount":3159600408
        },
        {  
            "address":"H4FPn4X1RfR9RQtmFzY6BRozUAfoR3Ejp",
            "txid":"8g4c86fn8N4BcUmAnNU1udZQzbXfPaDKkRoP9XHpngQu",
            "timestamp":"2018-08-08T20:06:28.000Z",
            "paidFee":0.00571,
            "paidAmount":2711826226
        },
        {  
            "address":"H4FPn4X1RfR9RQtmFzY6BRozUAfoR3Ejp",
            "txid":"6zS6MeC2eapWuTDXoQ97TRVqCzMVj1NGUeZSWhsWmQT6",
            "timestamp":"2018-08-08T03:57:50.000Z",
            "paidFee":0.00573,
            "paidAmount":3518292070
        },
        {  
            "address":"H4FPn4X1RfR9RQtmFzY6BRozUAfoR3Ejp",
            "txid":"FG5i9jhFHM7D1rmDgCqWSGgfJkCdYaMpZMryYqdkTUWL",
            "timestamp":"2018-08-08T03:44:25.000Z",
            "paidFee":0.00693,
            "paidAmount":2236903055
        },
        {  
            "address":"H4FPn4X1RfR9RQtmFzY6BRozUAfoR3Ejp",
            "txid":"CeuATN86Mz2bDuS1xffUz1A97PBBjPKj4u5xeT5G8Nje",
            "timestamp":"2018-08-07T22:53:42.000Z",
            "paidFee":0.00697,
            "paidAmount":3967841731
        },
        {  
            "address":"H4FPn4X1RfR9RQtmFzY6BRozUAfoR3Ejp",
            "txid":"425JitYEvemRgMZFWbv7tz7Mj7BHgpQCVTBpPTrBAbWv",
            "timestamp":"2018-08-07T15:31:46.000Z",
            "paidFee":0.00734,
            "paidAmount":3681148351
        },
        {  
            "address":"H4FPn4X1RfR9RQtmFzY6BRozUAfoR3Ejp",
            "txid":"4AM778kg8hb8MKfSWJ2UrfcA7KGhD2VKs5p1Ju6Gn5Nq",
            "timestamp":"2018-08-06T23:19:28.000Z",
            "paidFee":0.00787,
            "paidAmount":3721538454
        },
        {  
            "address":"H4FPn4X1RfR9RQtmFzY6BRozUAfoR3Ejp",
            "txid":"6fG4V6SGaPJ3644UKmbZChGCMyRQjK3cXtGDRVhcFXWJ",
            "timestamp":"2018-08-06T23:05:13.000Z",
            "paidFee":0.00912,
            "paidAmount":2542991363
        },
        {  
            "address":"H4FPn4X1RfR9RQtmFzY6BRozUAfoR3Ejp",
            "txid":"Ad8Woqq5NChCwk5ZnHwQbffydBU6nyWhpcSJ9ntuoxrQ",
            "timestamp":"2018-08-06T22:27:34.000Z",
            "paidFee":0.00913,
            "paidAmount":4067092270
        },
        {  
            "address":"H4FPn4X1RfR9RQtmFzY6BRozUAfoR3Ejp",
            "txid":"2TSzCCrDA4gXTdDDxNLWB4Ypbb47pEyTvMXuUKZcvHNz",
            "timestamp":"2018-08-06T22:00:38.000Z",
            "paidFee":0.00919,
            "paidAmount":3297885387
        },
        {  
            "address":"H4FPn4X1RfR9RQtmFzY6BRozUAfoR3Ejp",
            "txid":"b29upwbFKximBj2fKy6kEDeBemW5SoBaRG6E9hTasWz",
            "timestamp":"2018-08-06T21:03:48.000Z",
            "paidFee":0.00921,
            "paidAmount":3918358863
        },
        {  
            "address":"H4FPn4X1RfR9RQtmFzY6BRozUAfoR3Ejp",
            "txid":"iwkFRHxYk8yaDBfP5cYvMLQ9NhWYcpbh6BYxpbKy1Pa",
            "timestamp":"2018-08-06T20:24:58.000Z",
            "paidFee":0.00929,
            "paidAmount":4713287389
        },
        {  
            "address":"H4FPn4X1RfR9RQtmFzY6BRozUAfoR3Ejp",
            "txid":"DuWzM9RTvJceGEDRq3cmtehspBoZrArfP8RQsy4wMHNZ",
            "timestamp":"2018-08-06T18:17:22.000Z",
            "paidFee":0.00933,
            "paidAmount":4007092232
        },
        {  
            "address":"H4FPn4X1RfR9RQtmFzY6BRozUAfoR3Ejp",
            "txid":"5bikDTnLn8nNq4LHwZAv5BBEhqg4BARekGPgCdgXYzMw",
            "timestamp":"2018-08-06T18:12:07.000Z",
            "paidFee":0.00949,
            "paidAmount":4028467781
        },
        {  
            "address":"H4FPn4X1RfR9RQtmFzY6BRozUAfoR3Ejp",
            "txid":"6U1dkZ3m61FDtBBZLswWZxVNTBGeS5najQAcnRAYzwXE",
            "timestamp":"2018-08-06T07:10:14.000Z",
            "paidFee":0.0095,
            "paidAmount":3477845337
        },
        {  
            "address":"H4FPn4X1RfR9RQtmFzY6BRozUAfoR3Ejp",
            "txid":"GphPXzqiWhrc3YPERrhYuAm3PfFA3it6bu8vMVcRmGQk",
            "timestamp":"2018-08-06T01:10:33.000Z",
            "paidFee":0.01022,
            "paidAmount":38060
        },
        {  
            "address":"H4FPn4X1RfR9RQtmFzY6BRozUAfoR3Ejp",
            "txid":"3tdzYkNubQbU3AduCagtQHDuV6KaYrfcFedq57tRxEtW",
            "timestamp":"2018-08-05T23:30:11.000Z",
            "paidFee":0.01066,
            "paidAmount":4506015240
        },
        {  
            "address":"H4FPn4X1RfR9RQtmFzY6BRozUAfoR3Ejp",
            "txid":"3MebeZb4fMmMSkCbLsdJFG63MNhkogrupcwwHmjye6BR",
            "timestamp":"2018-08-05T21:52:47.000Z",
            "paidFee":0.01078,
            "paidAmount":0
        },
        {  
            "address":"H4FPn4X1RfR9RQtmFzY6BRozUAfoR3Ejp",
            "txid":"HpK9JuKHgzm7CQWtrMnLgwEiZwbtHKj3kdzb59yXa9yX",
            "timestamp":"2018-08-05T20:44:32.000Z",
            "paidFee":0.01092,
            "paidAmount":4410803964
        },
        {  
            "address":"H4FPn4X1RfR9RQtmFzY6BRozUAfoR3Ejp",
            "txid":"BfAxUNitdmDsn6AFUp3c3Hiq9AgWxXeNTRf2DXiVQZFU",
            "timestamp":"2018-08-05T20:21:42.000Z",
            "paidFee":0.011,
            "paidAmount":4818463279
        },
        {  
            "address":"H4FPn4X1RfR9RQtmFzY6BRozUAfoR3Ejp",
            "txid":"5JxQi8HaFjjWags4NpwHiPkm4cVVkAK8Y879HqZEdXbN",
            "timestamp":"2018-08-05T19:02:00.000Z",
            "paidFee":0.01103,
            "paidAmount":4742525093
        },
        {  
            "address":"H4FPn4X1RfR9RQtmFzY6BRozUAfoR3Ejp",
            "txid":"9Vf2UiZMAZDJwN7fxeDc4opz5GntVKKQ9uFJAAb7wC8p",
            "timestamp":"2018-08-05T18:54:50.000Z",
            "paidFee":0.01114,
            "paidAmount":3065165350
        },
        {  
            "address":"H4FPn4X1RfR9RQtmFzY6BRozUAfoR3Ejp",
            "txid":"CxVPo9hUjvSY2dVQGcNs2N95fGfSBSpKXPRXGuZb3CHV",
            "timestamp":"2018-08-05T16:23:46.000Z",
            "paidFee":0.01115,
            "paidAmount":5568204444
        },
        {  
            "address":"H4FPn4X1RfR9RQtmFzY6BRozUAfoR3Ejp",
            "txid":"XRdQedeeHpfuD1Bkwpe6iAH4AC8pUkrYYiz1SdzFeQ7",
            "timestamp":"2018-08-05T15:19:25.000Z",
            "paidFee":0.01133,
            "paidAmount":5153042394
        },
        {  
            "address":"H4FPn4X1RfR9RQtmFzY6BRozUAfoR3Ejp",
            "txid":"QdjV1hid7CDUGEX5LZLEBr1HKjhMLAe4qWwPW3ajFwc",
            "timestamp":"2018-08-05T12:57:38.000Z",
            "paidFee":0.01141,
            "paidAmount":5350067756
        },
        {  
            "address":"H4FPn4X1RfR9RQtmFzY6BRozUAfoR3Ejp",
            "txid":"BNujvfWxJvj1E3pj5CbJgy6xaVyfu1LT7N2zCH3m6cFg",
            "timestamp":"2018-08-04T02:03:59.000Z",
            "paidFee":0.01405,
            "paidAmount":4084182552
        },
        {  
            "address":"H4FPn4X1RfR9RQtmFzY6BRozUAfoR3Ejp",
            "txid":"BeCnRdu7iYV3x3g6cmoMxjfTPRTYJ5YhT29qjLZ6g736",
            "timestamp":"2018-08-04T01:13:18.000Z",
            "paidFee":0.01407,
            "paidAmount":4636876578
        },
        {  
            "address":"H4FPn4X1RfR9RQtmFzY6BRozUAfoR3Ejp",
            "txid":"7HppyGgYh57VRhstkzAPptoZGRNDKbhHyKUodfqJXL9J",
            "timestamp":"2018-08-04T00:16:41.000Z",
            "paidFee":0.01417,
            "paidAmount":4981948226
        },
        {  
            "address":"H4FPn4X1RfR9RQtmFzY6BRozUAfoR3Ejp",
            "txid":"2HNLquA1VgUzP6F7TJpafotyq63fWXy5jWGihbwYj8hx",
            "timestamp":"2018-08-03T23:34:00.000Z",
            "paidFee":0.01419,
            "paidAmount":4458633839
        },
        {  
            "address":"H4FPn4X1RfR9RQtmFzY6BRozUAfoR3Ejp",
            "txid":"3HH8hN7MTm4vpmZ4EuUcsnFxU6DDnVfBX2idwYTf8VJc",
            "timestamp":"2018-08-03T22:43:43.000Z",
            "paidFee":0.01425,
            "paidAmount":2459207286
        },
        {  
            "address":"H4FPn4X1RfR9RQtmFzY6BRozUAfoR3Ejp",
            "txid":"6inctg2SPLdKvaYB96t2dsKhXeYAo6JrjLFaubM5ERjn",
            "timestamp":"2018-08-03T22:22:17.000Z",
            "paidFee":0.01431,
            "paidAmount":4031225676
        },
        {  
            "address":"H4FPn4X1RfR9RQtmFzY6BRozUAfoR3Ejp",
            "txid":"8eanH5BYnbFyxB3E3RvT2ZCXoCAECa4pVJDYWbZSmUce",
            "timestamp":"2018-08-03T21:24:35.000Z",
            "paidFee":0.01433,
            "paidAmount":3996904119
        },
        {  
            "address":"H4FPn4X1RfR9RQtmFzY6BRozUAfoR3Ejp",
            "txid":"Af8tRFSDnkd5axKadUqf8ebbbk3MRMvzsDBZrqnQwxpw",
            "timestamp":"2018-08-03T15:55:15.000Z",
            "paidFee":0.01459,
            "paidAmount":2711874836
        },
        {  
            "address":"H4FPn4X1RfR9RQtmFzY6BRozUAfoR3Ejp",
            "txid":"DhzQ1D5Nzroed4YXTKP2G1TYeSwf5D3Gh5M6vsRxWdtW",
            "timestamp":"2018-08-03T13:21:27.000Z",
            "paidFee":0.0148,
            "paidAmount":3415968656
        },
        {  
            "address":"H4FPn4X1RfR9RQtmFzY6BRozUAfoR3Ejp",
            "txid":"AduvMCf2E6Ks1Y5pC7VvcKniEZdrrtTQZWPYj7P8GfgY",
            "timestamp":"2018-08-03T04:03:33.000Z",
            "paidFee":0.01557,
            "paidAmount":3612391288
        },
        {  
            "address":"H4FPn4X1RfR9RQtmFzY6BRozUAfoR3Ejp",
            "txid":"CTCV8gCDVWw2msQABqHkYefqKnhpszsSsJjDHC47Nm69",
            "timestamp":"2018-08-03T00:36:40.000Z",
            "paidFee":0.01569,
            "paidAmount":3982135826
        },
        {  
            "address":"H4FPn4X1RfR9RQtmFzY6BRozUAfoR3Ejp",
            "txid":"22iNjEJur9vrkykaQdagkYkoJN9tiwoorxkLJ99cEt2V",
            "timestamp":"2018-08-02T23:08:15.000Z",
            "paidFee":0.01595,
            "paidAmount":3014391758
        },
        {  
            "address":"H4FPn4X1RfR9RQtmFzY6BRozUAfoR3Ejp",
            "txid":"4NTcs343ZYADoNXodr81aBrcezP4acWFgs9StmKA3uv5",
            "timestamp":"2018-08-02T12:56:50.000Z",
            "paidFee":0.01659,
            "paidAmount":3938159715
        },
        {  
            "address":"H4FPn4X1RfR9RQtmFzY6BRozUAfoR3Ejp",
            "txid":"4dEJ1XvN5z33UTNFvn5NNTkQ2TvDAjk3bKJA6vLyamjj",
            "timestamp":"2018-08-02T11:51:01.000Z",
            "paidFee":0.01675,
            "paidAmount":3667981503
        },
        {  
            "address":"H4FPn4X1RfR9RQtmFzY6BRozUAfoR3Ejp",
            "txid":"5CVmkn9ScbuiniNUqM5gnihaLpo3F9oPVpW1vDewNMKi",
            "timestamp":"2018-08-02T10:36:01.000Z",
            "paidFee":0.01691,
            "paidAmount":2701531560
        },
        {  
            "address":"H4FPn4X1RfR9RQtmFzY6BRozUAfoR3Ejp",
            "txid":"6s5V9j7Mny17jTNBBN1HLyeGALGq5rqAXp8HAMBHYTa7",
            "timestamp":"2018-08-02T09:10:14.000Z",
            "paidFee":0.01703,
            "paidAmount":6964402716
        },
        {  
            "address":"H4FPn4X1RfR9RQtmFzY6BRozUAfoR3Ejp",
            "txid":"6G9skw6N9Sjoagn3ggL3nVMvRspNNLyYHrq9wNaEd62B",
            "timestamp":"2018-08-02T07:32:00.000Z",
            "paidFee":0.01704,
            "paidAmount":4342341307
        },
        {  
            "address":"H4FPn4X1RfR9RQtmFzY6BRozUAfoR3Ejp",
            "txid":"3H67RFM1njs61cf3edKAscWXVuL4tiwo3avRRCkCoHui",
            "timestamp":"2018-08-02T07:28:43.000Z",
            "paidFee":0.01717,
            "paidAmount":2487895980
        },
        {  
            "address":"H4FPn4X1RfR9RQtmFzY6BRozUAfoR3Ejp",
            "txid":"ETv5ZfchNSDpPscgLtZ7vxDvot5MwZDN5QQYdrqWwZrP",
            "timestamp":"2018-08-02T06:44:26.000Z",
            "paidFee":0.01721,
            "paidAmount":4314209386
        },
        {  
            "address":"H4FPn4X1RfR9RQtmFzY6BRozUAfoR3Ejp",
            "txid":"Ddhp335Uf8zPFmBEWD8cCckjHXrr5fbofGB9ZPgpRN89",
            "timestamp":"2018-08-02T04:21:00.000Z",
            "paidFee":0.01735,
            "paidAmount":2116690411
        },
        {  
            "address":"H4FPn4X1RfR9RQtmFzY6BRozUAfoR3Ejp",
            "txid":"5meqK1QihhJ4Y7Mt5bL6FRNwGziPUuREnWBFaE1nmBeq",
            "timestamp":"2018-08-02T02:20:52.000Z",
            "paidFee":0.0174,
            "paidAmount":4370412461
        },
        {  
            "address":"H4FPn4X1RfR9RQtmFzY6BRozUAfoR3Ejp",
            "txid":"6FP9jiKzTCwsRNhHQAHpEBDjTuhH8RsZyeqMMDUnkiz7",
            "timestamp":"2018-08-02T02:02:58.000Z",
            "paidFee":0.01754,
            "paidAmount":5512412200
        },
        {  
            "address":"H4FPn4X1RfR9RQtmFzY6BRozUAfoR3Ejp",
            "txid":"EiyNXNuqYnU5viLutRkVv1URtjRa65GjRkFr4hRvLfmC",
            "timestamp":"2018-08-01T21:38:04.000Z",
            "paidFee":0.01786,
            "paidAmount":3896082950
        },
        {  
            "address":"H4FPn4X1RfR9RQtmFzY6BRozUAfoR3Ejp",
            "txid":"Gt7v6qEreApCJmwPdySmeTY95UwJg7nMMKPQASU3hCjQ",
            "timestamp":"2018-08-01T21:03:53.000Z",
            "paidFee":0.0179,
            "paidAmount":4044901611
        },
        {  
            "address":"H4FPn4X1RfR9RQtmFzY6BRozUAfoR3Ejp",
            "txid":"HMJu23YvtuVgDu1dZAeQQ291XH8L5oWnjvk8hFjptQPE",
            "timestamp":"2018-08-01T18:37:54.000Z",
            "paidFee":0.01794,
            "paidAmount":4732591438
        },
        {  
            "address":"H4FPn4X1RfR9RQtmFzY6BRozUAfoR3Ejp",
            "txid":"E2Y83z5qTpgSArvNyEsnJjDB4j2HwKY9ZZAHPhxDPkXT",
            "timestamp":"2018-08-01T17:12:39.000Z",
            "paidFee":0.01811,
            "paidAmount":4464964511
        },
        {  
            "address":"H4FPn4X1RfR9RQtmFzY6BRozUAfoR3Ejp",
            "txid":"82wgzFTGr9rEw8CKYa7Nx6UNTf8zPo8fzhmPfp8EaxKV",
            "timestamp":"2018-08-01T14:23:06.000Z",
            "paidFee":0.01825,
            "paidAmount":3875054485
        },
        {  
            "address":"H4FPn4X1RfR9RQtmFzY6BRozUAfoR3Ejp",
            "txid":"4ZTc9m36nJJSb2hei9XCKjd6enHYN8qneDFGqPppW9Sp",
            "timestamp":"2018-08-01T08:05:49.000Z",
            "paidFee":0.01871,
            "paidAmount":3806805209
        },
        {  
            "address":"H4FPn4X1RfR9RQtmFzY6BRozUAfoR3Ejp",
            "txid":"6AirjP22s5UoizTZZQbk6RkCrBwP7tRSU6UZUDRz4B4w",
            "timestamp":"2018-08-01T05:46:42.000Z",
            "paidFee":0.01897,
            "paidAmount":3999400549
        },
        {  
            "address":"H4FPn4X1RfR9RQtmFzY6BRozUAfoR3Ejp",
            "txid":"DtBUjFZXsMBcEHoSahbxku8797viAAcgvoC9cXWQ6dkM",
            "timestamp":"2018-08-01T04:34:12.000Z",
            "paidFee":0.01905,
            "paidAmount":3012013895
        },
        {  
            "address":"H4FPn4X1RfR9RQtmFzY6BRozUAfoR3Ejp",
            "txid":"86miQt2cCSCzU7eQmyYcZgkJYojSQEXqZaTdQepMprua",
            "timestamp":"2018-08-01T03:43:50.000Z",
            "paidFee":0.01918,
            "paidAmount":7510127535
        },
        {  
            "address":"H4FPn4X1RfR9RQtmFzY6BRozUAfoR3Ejp",
            "txid":"6qQHfGR3JSymf4ENhSBfQ5JaGN6sBRHDB9ZdAfxkUhx",
            "timestamp":"2018-08-01T02:28:43.000Z",
            "paidFee":0.01921,
            "paidAmount":4503441560
        },
        {  
            "address":"H4FPn4X1RfR9RQtmFzY6BRozUAfoR3Ejp",
            "txid":"7EMyHc2vWxBiMoDqr9k3yVPLZrafPi6EsdMyJQMu8JLX",
            "timestamp":"2018-08-01T00:14:41.000Z",
            "paidFee":0.01937,
            "paidAmount":4445621030
        },
        {  
            "address":"H4FPn4X1RfR9RQtmFzY6BRozUAfoR3Ejp",
            "txid":"HvyM2VuoEPkrqeDCbXZwqQSU8HBnhA5o4LMjcFDaPjdh",
            "timestamp":"2018-07-31T23:16:58.000Z",
            "paidFee":0.01946,
            "paidAmount":4636030523
        },
        {  
            "address":"H4FPn4X1RfR9RQtmFzY6BRozUAfoR3Ejp",
            "txid":"Cg8X3FPTFBHiQFcMgokPGv57zU2kkkfS8DqZfcjrNP9q",
            "timestamp":"2018-07-31T19:40:41.000Z",
            "paidFee":0.01977,
            "paidAmount":4863649757
        },
        {  
            "address":"H4FPn4X1RfR9RQtmFzY6BRozUAfoR3Ejp",
            "txid":"6yFCfTGuuMdQZB7zcHbDH8h1KPQRwkCV9i5es1UPTX2C",
            "timestamp":"2018-07-31T19:32:52.000Z",
            "paidFee":0.01982,
            "paidAmount":1510005256
        },
        {  
            "address":"H4FPn4X1RfR9RQtmFzY6BRozUAfoR3Ejp",
            "txid":"DXMavzLfSfuL1YYY8fLLiCnkeoEAkShErmKdT63PExt7",
            "timestamp":"2018-07-31T18:02:58.000Z",
            "paidFee":0.01983,
            "paidAmount":5359485769
        },
        {  
            "address":"H4FPn4X1RfR9RQtmFzY6BRozUAfoR3Ejp",
            "txid":"4PwcSAie9xyb8ujXMG3xwBF59yR8VjQ94oA4CRNLg73J",
            "timestamp":"2018-07-31T07:27:02.000Z",
            "paidFee":0.02066,
            "paidAmount":4616293078
        },
        {  
            "address":"H4FPn4X1RfR9RQtmFzY6BRozUAfoR3Ejp",
            "txid":"4NzGsvf8LQdcHVWYqwpjoQ24BCrQ2z69gomBTDKf7AVR",
            "timestamp":"2018-07-30T14:33:25.000Z",
            "paidFee":0.02188,
            "paidAmount":4188026990
        },
        {  
            "address":"H4FPn4X1RfR9RQtmFzY6BRozUAfoR3Ejp",
            "txid":"G2QyTPUEc9FUW1krfmY6QVQzLnYddreBCETCMf8boTp7",
            "timestamp":"2018-07-30T06:32:59.000Z",
            "paidFee":0.02226,
            "paidAmount":7939405626
        }
        ],
        "minerFee":0.0025,
        "totalPaid":864.607963365
    }
 }